com/__init__.py
com/sdey/__init__.py
com/sdey/info/__init__.py
com/sdey/info/sys_argv.py
com/sdey/info/sys_module.py
sdey_message-0.1.dist-info/METADATA
sdey_message-0.1.dist-info/WHEEL
sdey_message-0.1.dist-info/top_level.txt
sdey_message-0.1.dist-info/RECORD
