Metadata-Version: 2.1
Name: sdey-message
Version: 0.1
Summary: Get Sdey Informatin
Home-page: http://www.sdey.net
Author: 周合永
License: UNKNOWN
Platform: UNKNOWN
